{
	"configurations" : 
	[
		{
			"directories" : 
			[
				{
					"build" : ".",
					"jsonFile" : "directory-.-Debug-d0094a50bb2071803777.json",
					"minimumCMakeVersion" : 
					{
						"string" : "3.22"
					},
					"projectIndex" : 0,
					"source" : ".",
					"targetIndexes" : 
					[
						0
					]
				}
			],
			"name" : "Debug",
			"projects" : 
			[
				{
					"directoryIndexes" : 
					[
						0
					],
					"name" : "practice9_1",
					"targetIndexes" : 
					[
						0
					]
				}
			],
			"targets" : 
			[
				{
					"directoryIndex" : 0,
					"id" : "practice9_1::@6890427a1f51a3e7e1df",
					"jsonFile" : "target-practice9_1-Debug-d51bcc87e9b0a6309c21.json",
					"name" : "practice9_1",
					"projectIndex" : 0
				}
			]
		}
	],
	"kind" : "codemodel",
	"paths" : 
	{
		"build" : "C:/Users/j-t0417/CLionProjects/practice9_1/cmake-build-debug",
		"source" : "C:/Users/j-t0417/CLionProjects/practice9_1"
	},
	"version" : 
	{
		"major" : 2,
		"minor" : 3
	}
}
